vibedazi/__init__.py
vibedazi/server.py
vibedazi/store.py
vibedazi/web.py
vibedazi/static/app.js
vibedazi/static/index.html
vibedazi/static/styles.css
vibedazi_mcp-0.2.1.dist-info/METADATA
vibedazi_mcp-0.2.1.dist-info/WHEEL
vibedazi_mcp-0.2.1.dist-info/entry_points.txt
vibedazi_mcp-0.2.1.dist-info/top_level.txt
vibedazi_mcp-0.2.1.dist-info/RECORD
