Metadata-Version: 2.4
Name: vibedazi-mcp
Version: 0.2.1
Summary: vibeDazi MCP server for team-shared vibe logs with git context
Author-email: vibeDazi Team <dev@example.com>
License: MIT
Project-URL: Homepage, https://github.com/your-org/vibeDazi
Project-URL: Repository, https://github.com/your-org/vibeDazi.git
Project-URL: Issues, https://github.com/your-org/vibeDazi/issues
Keywords: mcp,vibe,team,git,logging
Requires-Python: >=3.9
Requires-Dist: mcp>=1.14.0
Requires-Dist: anyio>=4.5.0
Requires-Dist: starlette>=0.48.0
Requires-Dist: uvicorn>=0.37.0
